fontawesome_5/__init__.py
fontawesome_5/app_settings.py
fontawesome_5/fields.py
fontawesome_5/forms.py
fontawesome_5/icons.json
fontawesome_5/icons_semantic_ui.json
fontawesome_5/models.py
fontawesome_5/renderers.py
fontawesome_5/shims.py
fontawesome_5/utils.py
fontawesome_5/widgets.py
fontawesome_5/static/fontawesome_5/css/all.min.css
fontawesome_5/static/fontawesome_5/js/all.min.js
fontawesome_5/static/fontawesome_5/webfonts/fa-brands-400.eot
fontawesome_5/static/fontawesome_5/webfonts/fa-brands-400.svg
fontawesome_5/static/fontawesome_5/webfonts/fa-brands-400.ttf
fontawesome_5/static/fontawesome_5/webfonts/fa-brands-400.woff
fontawesome_5/static/fontawesome_5/webfonts/fa-brands-400.woff2
fontawesome_5/static/fontawesome_5/webfonts/fa-regular-400.eot
fontawesome_5/static/fontawesome_5/webfonts/fa-regular-400.svg
fontawesome_5/static/fontawesome_5/webfonts/fa-regular-400.ttf
fontawesome_5/static/fontawesome_5/webfonts/fa-regular-400.woff
fontawesome_5/static/fontawesome_5/webfonts/fa-regular-400.woff2
fontawesome_5/static/fontawesome_5/webfonts/fa-solid-900.eot
fontawesome_5/static/fontawesome_5/webfonts/fa-solid-900.svg
fontawesome_5/static/fontawesome_5/webfonts/fa-solid-900.ttf
fontawesome_5/static/fontawesome_5/webfonts/fa-solid-900.woff
fontawesome_5/static/fontawesome_5/webfonts/fa-solid-900.woff2
fontawesome_5/templates/fontawesome_5/select.html
fontawesome_5/templatetags/__init__.py
fontawesome_5/templatetags/fontawesome_5.py
django_fontawesome_5_renewed-1.0.19.dist-info/LICENSE
django_fontawesome_5_renewed-1.0.19.dist-info/METADATA
django_fontawesome_5_renewed-1.0.19.dist-info/WHEEL
django_fontawesome_5_renewed-1.0.19.dist-info/top_level.txt
django_fontawesome_5_renewed-1.0.19.dist-info/RECORD
