Metadata-Version: 2.1
Name: django-fontawesome-5-renewed
Version: 1.0.19
Summary: A fork of a utility for using icons in models, forms, and templates.
Home-page: https://github.com/FruitPassion/django-fontawesome-5
Author: Raphael Boudin
Author-email: raphael.boudin@protonmail.com
License: BSD License
Classifier: Environment :: Web Environment
Classifier: Framework :: Django
Classifier: Intended Audience :: Developers
Classifier: License :: OSI Approved :: BSD License
Classifier: Operating System :: OS Independent
Classifier: Topic :: Utilities
License-File: LICENSE
Requires-Dist: Django (>=4)
